executor/__init__.py
executor/duckdb_executor.py
executor/executor.py
executor_invest_helper-0.1.5.dist-info/METADATA
executor_invest_helper-0.1.5.dist-info/WHEEL
executor_invest_helper-0.1.5.dist-info/top_level.txt
executor_invest_helper-0.1.5.dist-info/RECORD
