Metadata-Version: 2.1
Name: executor-invest-helper
Version: 0.1.5
Summary: Database Executor for Invest Helper
Home-page: https://github.com/sazonovvladimir/invest_helper_bot
Author: Invest Guru
Author-email: example@gmail.com
License: UNKNOWN
Platform: UNKNOWN
Classifier: Programming Language :: Python :: 3
Classifier: License :: OSI Approved :: MIT License
Classifier: Operating System :: OS Independent
Requires-Python: >=3.5
